{"cameraMode":{"drawMode":0,"name":"Shaded","section":"Shading Mode"},"sceneLighting":false,"audioPlay":false,"sceneViewState":{"showFog":true,"showMaterialUpdate":false,"showSkybox":false,"showFlares":true,"showImageEffects":true,"showParticleSystems":true},"in2DMode":false,"pivot":{"x":-54.93486785888672,"y":-15.928375244140625,"z":8.685519218444825},"rotation":{"x":0.10357397049665451,"y":-0.6484695672988892,"z":0.088324636220932,"w":0.7493353486061096},"size":34.83694839477539,"orthographic":false}